xpdeep/__init__.py
xpdeep-0.0.0.dist-info/METADATA
xpdeep-0.0.0.dist-info/WHEEL
xpdeep-0.0.0.dist-info/top_level.txt
xpdeep-0.0.0.dist-info/RECORD
