Metadata-Version: 2.1
Name: xpdeep
Version: 0.0.0
Summary: Coming soon
Author-email: Benjamin GIRARD <support@xpdeep.com>
